tacocompression/__init__.py
tacocompression/__main__.py
tacocompression/compression.py
tacocompression/functions.py
tacocompression/input_output.py
tacocompression-0.9.6.dist-info/licenses/LICENSE
tacocompression-0.9.6.dist-info/METADATA
tacocompression-0.9.6.dist-info/WHEEL
tacocompression-0.9.6.dist-info/top_level.txt
tacocompression-0.9.6.dist-info/RECORD
