Metadata-Version: 2.4
Name: tacocompression
Version: 0.9.6
Summary: Implementation of TACO: A Lightweight Tree-Based Approximate Compression Method for Time Series
Author-email: André Bauer <abauer7@illinoistech.edu>, Michael Stenger <michael.stenger@uni-wuerzburg.de>
License-Expression: MIT
Project-URL: Homepage, https://github.com/ms2017/taco-compression
Project-URL: Issues, https://github.com/ms2017/taco-compression/issues
Classifier: Programming Language :: Python :: 3
Classifier: Operating System :: OS Independent
Requires-Python: >=3.9
License-File: LICENSE
Requires-Dist: numpy>=1.23.1
Dynamic: license-file
